responsive/__init__.py
responsive/constants.py
responsive/data.py
responsive/observer.py
responsive/subject.py
responsive/wrapper.py
responsive_data-1.0.4.dist-info/LICENSE
responsive_data-1.0.4.dist-info/METADATA
responsive_data-1.0.4.dist-info/WHEEL
responsive_data-1.0.4.dist-info/top_level.txt
responsive_data-1.0.4.dist-info/RECORD
