Metadata-Version: 2.1
Name: responsive-data
Version: 1.0.4
Summary: Framework for converting data to be responsive
Home-page: https://github.com/thomas-lehmann-private/responsive-data
Author: Thomas Lehmann
Author-email: thomas.lehmann.private@gmail.com
License: MIT
Platform: UNKNOWN
Classifier: License :: OSI Approved :: MIT License
Classifier: Programming Language :: Python :: 3
Classifier: Programming Language :: Python :: 3.10
License-File: LICENSE
